pgark/__about__.py
pgark/__init__.py
pgark/cli.py
pgark/exceptions.py
pgark/mylog.py
pgark/task_meta.py
pgark/wayback.py
pgark/archivers/wayback.py
pgark-0.0.3.dist-info/LICENSE
pgark-0.0.3.dist-info/METADATA
pgark-0.0.3.dist-info/WHEEL
pgark-0.0.3.dist-info/entry_points.txt
pgark-0.0.3.dist-info/top_level.txt
pgark-0.0.3.dist-info/RECORD
