Metadata-Version: 2.1
Name: pgark
Version: 0.0.3
Summary: Python library and CLI for archiving URLs on popular services like Wayback Machine
Home-page: https://www.github.com/dannguyen/pgark
Author: Dan Nguyen
Author-email: dansonguyen@gmail.com
License: UNKNOWN
Project-URL: Project, https://www.github.com/dannguyen/pgark
Project-URL: Source, https://www.github.com/dannguyen/pgark
Project-URL: Tracker, https://www.github.com/dannguyen/pgark/issues
Platform: UNKNOWN
Classifier: Development Status :: 3 - Alpha
Classifier: Operating System :: OS Independent
Classifier: Intended Audience :: Developers
Classifier: Programming Language :: Python
Classifier: Programming Language :: Python :: 3
Classifier: Programming Language :: Python :: 3.6
Classifier: Programming Language :: Python :: 3.7
Classifier: Programming Language :: Python :: 3.8
Classifier: License :: OSI Approved :: MIT License
Requires-Python: >=3.6
Requires-Dist: certifi (==2020.6.20)
Requires-Dist: chardet (==3.0.4)
Requires-Dist: click (==7.1.2)
Requires-Dist: commonmark (==0.9.1)
Requires-Dist: cssselect (==1.1.0)
Requires-Dist: lxml (==4.5.2)
Requires-Dist: requests (==2.24.0)
Requires-Dist: rich (==6.0.0)
Requires-Dist: typing-extensions (==3.7.4.3)
Requires-Dist: idna (==2.10) ; python_version >= "2.7" and python_version not in "3.0, 3.1, 3.2, 3.3"
Requires-Dist: colorama (==0.4.3) ; python_version >= "2.7" and python_version not in "3.0, 3.1, 3.2, 3.3, 3.4"
Requires-Dist: urllib3 (==1.25.10) ; python_version >= "2.7" and python_version not in "3.0, 3.1, 3.2, 3.3, 3.4" and python_version < "4"
Requires-Dist: pygments (==2.6.1) ; python_version >= "3.5"
Provides-Extra: dev
Requires-Dist: appdirs (==1.4.4) ; extra == 'dev'
Requires-Dist: black (==20.8b1) ; extra == 'dev'
Requires-Dist: certifi (==2020.6.20) ; extra == 'dev'
Requires-Dist: chardet (==3.0.4) ; extra == 'dev'
Requires-Dist: click (==7.1.2) ; extra == 'dev'
Requires-Dist: coverage (==5.2.1) ; extra == 'dev'
Requires-Dist: freezegun (==1.0.0) ; extra == 'dev'
Requires-Dist: iniconfig (==1.0.1) ; extra == 'dev'
Requires-Dist: mypy-extensions (==0.4.3) ; extra == 'dev'
Requires-Dist: pathspec (==0.8.0) ; extra == 'dev'
Requires-Dist: pkginfo (==1.5.0.1) ; extra == 'dev'
Requires-Dist: pytest (==6.0.1) ; extra == 'dev'
Requires-Dist: readme-renderer (==26.0) ; extra == 'dev'
Requires-Dist: regex (==2020.7.14) ; extra == 'dev'
Requires-Dist: requests (==2.24.0) ; extra == 'dev'
Requires-Dist: requests-toolbelt (==0.9.1) ; extra == 'dev'
Requires-Dist: responses (==0.12.0) ; extra == 'dev'
Requires-Dist: rfc3986 (==1.4.0) ; extra == 'dev'
Requires-Dist: toml (==0.10.1) ; extra == 'dev'
Requires-Dist: twine (==3.2.0) ; extra == 'dev'
Requires-Dist: typed-ast (==1.4.1) ; extra == 'dev'
Requires-Dist: typing-extensions (==3.7.4.3) ; extra == 'dev'
Requires-Dist: webencodings (==0.5.1) ; extra == 'dev'
Requires-Dist: wheel (==0.35.1) ; extra == 'dev'
Requires-Dist: pyparsing (==2.4.7) ; (python_version >= "2.6" and python_version not in "3.0, 3.1, 3.2, 3.3") and extra == 'dev'
Requires-Dist: tqdm (==4.48.2) ; (python_version >= "2.6" and python_version not in "3.0, 3.1, 3.2, 3.3") and extra == 'dev'
Requires-Dist: attrs (==20.2.0) ; (python_version >= "2.7" and python_version not in "3.0, 3.1, 3.2, 3.3") and extra == 'dev'
Requires-Dist: idna (==2.10) ; (python_version >= "2.7" and python_version not in "3.0, 3.1, 3.2, 3.3") and extra == 'dev'
Requires-Dist: packaging (==20.4) ; (python_version >= "2.7" and python_version not in "3.0, 3.1, 3.2, 3.3") and extra == 'dev'
Requires-Dist: pluggy (==0.13.1) ; (python_version >= "2.7" and python_version not in "3.0, 3.1, 3.2, 3.3") and extra == 'dev'
Requires-Dist: py (==1.9.0) ; (python_version >= "2.7" and python_version not in "3.0, 3.1, 3.2, 3.3") and extra == 'dev'
Requires-Dist: python-dateutil (==2.8.1) ; (python_version >= "2.7" and python_version not in "3.0, 3.1, 3.2, 3.3") and extra == 'dev'
Requires-Dist: six (==1.15.0) ; (python_version >= "2.7" and python_version not in "3.0, 3.1, 3.2, 3.3") and extra == 'dev'
Requires-Dist: bleach (==3.1.5) ; (python_version >= "2.7" and python_version not in "3.0, 3.1, 3.2, 3.3, 3.4") and extra == 'dev'
Requires-Dist: colorama (==0.4.3) ; (python_version >= "2.7" and python_version not in "3.0, 3.1, 3.2, 3.3, 3.4") and extra == 'dev'
Requires-Dist: docutils (==0.16) ; (python_version >= "2.7" and python_version not in "3.0, 3.1, 3.2, 3.3, 3.4") and extra == 'dev'
Requires-Dist: urllib3 (==1.25.10) ; (python_version >= "2.7" and python_version not in "3.0, 3.1, 3.2, 3.3, 3.4" and python_version < "4") and extra == 'dev'
Requires-Dist: more-itertools (==8.5.0) ; (python_version >= "3.5") and extra == 'dev'
Requires-Dist: pygments (==2.6.1) ; (python_version >= "3.5") and extra == 'dev'
Requires-Dist: keyring (==21.4.0) ; (python_version >= "3.6") and extra == 'dev'
